django_s3sign-0.6.1.dist-info/licenses/LICENSE
s3sign/__init__.py
s3sign/models.py
s3sign/urls.py
s3sign/utils.py
s3sign/views.py
s3sign/__pycache__/__init__.cpython-314.pyc
s3sign/__pycache__/models.cpython-314.pyc
s3sign/__pycache__/views.cpython-314.pyc
s3sign/static/s3sign/js/s3upload.js
s3sign/tests/__init__.py
s3sign/tests/test_views.py
s3sign/tests/__pycache__/__init__.cpython-314.pyc
s3sign/tests/__pycache__/test_views.cpython-314.pyc
django_s3sign-0.6.1.dist-info/METADATA
django_s3sign-0.6.1.dist-info/WHEEL
django_s3sign-0.6.1.dist-info/top_level.txt
django_s3sign-0.6.1.dist-info/RECORD
