Metadata-Version: 2.4
Name: django-s3sign
Version: 0.6.1
Summary: Django view for AWS S3 signing
Home-page: https://github.com/ccnmtl/django-s3sign
Author: Anders Pearson
Author-email: ctl-dev@columbia.edu
License: GPL3
Platform: any
License-File: LICENSE
Requires-Dist: Django>=4.2
Requires-Dist: boto3
Requires-Dist: botocore
Requires-Dist: six
Dynamic: author
Dynamic: author-email
Dynamic: description
Dynamic: description-content-type
Dynamic: home-page
Dynamic: license
Dynamic: license-file
Dynamic: platform
Dynamic: requires-dist
Dynamic: summary
